{"BUF602xD":"<svg xmlns=\"http://www.w3.org/2000/svg\" viewBox=\"-8.84 -8.84 17.68 17.68\"><style>.s{stroke:rgb(132,0,0);stroke-linecap:round;stroke-linejoin:round;fill:none}.p{stroke:rgb(132,0,0);stroke-width:0.1524;stroke-linecap:round;fill:none}.fo{fill:rgb(132,0,0)}.fb{fill:rgb(255,255,194)}</style><polygon class=\"s fb\" points=\"5.08,0 -5.08,5.08 -5.08,-5.08 5.08,0\" stroke-width=\"0.25\"/><line class=\"p\" x1=\"-7.62\" y1=\"0\" x2=\"-5.08\" y2=\"0\"/><line class=\"p\" x1=\"-5.08\" y1=\"5.08\" x2=\"-2.54\" y2=\"5.08\"/><line class=\"p\" x1=\"-5.08\" y1=\"2.54\" x2=\"-2.54\" y2=\"2.54\"/><line class=\"p\" x1=\"-5.08\" y1=\"-2.54\" x2=\"-2.54\" y2=\"-2.54\"/><line class=\"p\" x1=\"-2.54\" y1=\"7.62\" x2=\"-2.54\" y2=\"3.81\"/><line class=\"p\" x1=\"-2.54\" y1=\"-7.62\" x2=\"-2.54\" y2=\"-3.81\"/><line class=\"p\" x1=\"0\" y1=\"-7.62\" x2=\"0\" y2=\"-2.54\"/><line class=\"p\" x1=\"7.62\" y1=\"0\" x2=\"5.08\" y2=\"0\"/></svg>","BUF602xDBV":"<svg xmlns=\"http://www.w3.org/2000/svg\" viewBox=\"-8.84 -8.84 17.68 17.68\"><style>.s{stroke:rgb(132,0,0);stroke-linecap:round;stroke-linejoin:round;fill:none}.p{stroke:rgb(132,0,0);stroke-width:0.1524;stroke-linecap:round;fill:none}.fo{fill:rgb(132,0,0)}.fb{fill:rgb(255,255,194)}</style><polygon class=\"s fb\" points=\"5.08,0 -5.08,5.08 -5.08,-5.08 5.08,0\" stroke-width=\"0.25\"/><line class=\"p\" x1=\"-7.62\" y1=\"0\" x2=\"-5.08\" y2=\"0\"/><line class=\"p\" x1=\"-2.54\" y1=\"7.62\" x2=\"-2.54\" y2=\"3.81\"/><line class=\"p\" x1=\"-2.54\" y1=\"-7.62\" x2=\"-2.54\" y2=\"-3.81\"/><line class=\"p\" x1=\"0\" y1=\"-7.62\" x2=\"0\" y2=\"-2.54\"/><line class=\"p\" x1=\"7.62\" y1=\"0\" x2=\"5.08\" y2=\"0\"/></svg>","BUF634AxDDA":"<svg xmlns=\"http://www.w3.org/2000/svg\" viewBox=\"-8.84 -8.84 17.68 17.68\"><style>.s{stroke:rgb(132,0,0);stroke-linecap:round;stroke-linejoin:round;fill:none}.p{stroke:rgb(132,0,0);stroke-width:0.1524;stroke-linecap:round;fill:none}.fo{fill:rgb(132,0,0)}.fb{fill:rgb(255,255,194)}</style><polygon class=\"s fb\" points=\"5.08,0 -5.08,5.08 -5.08,-5.08 5.08,0\" stroke-width=\"0.25\"/><line class=\"p\" x1=\"0\" y1=\"-7.62\" x2=\"0\" y2=\"-2.54\"/><line class=\"p\" x1=\"-7.62\" y1=\"0\" x2=\"-5.08\" y2=\"0\"/><line class=\"p\" x1=\"-5.08\" y1=\"5.08\" x2=\"-2.54\" y2=\"5.08\"/><line class=\"p\" x1=\"-5.08\" y1=\"2.54\" x2=\"-2.54\" y2=\"2.54\"/><line class=\"p\" x1=\"-5.08\" y1=\"-2.54\" x2=\"-2.54\" y2=\"-2.54\"/><line class=\"p\" x1=\"-2.54\" y1=\"7.62\" x2=\"-2.54\" y2=\"3.81\"/><line class=\"p\" x1=\"-2.54\" y1=\"-7.62\" x2=\"-2.54\" y2=\"-3.81\"/><line class=\"p\" x1=\"2.54\" y1=\"-7.62\" x2=\"2.54\" y2=\"-1.27\"/><line class=\"p\" x1=\"7.62\" y1=\"0\" x2=\"5.08\" y2=\"0\"/></svg>","BUF634U":"<svg xmlns=\"http://www.w3.org/2000/svg\" viewBox=\"-8.84 -8.84 17.68 17.68\"><style>.s{stroke:rgb(132,0,0);stroke-linecap:round;stroke-linejoin:round;fill:none}.p{stroke:rgb(132,0,0);stroke-width:0.1524;stroke-linecap:round;fill:none}.fo{fill:rgb(132,0,0)}.fb{fill:rgb(255,255,194)}</style><polygon class=\"s fb\" points=\"5.08,0 -5.08,5.08 -5.08,-5.08 5.08,0\" stroke-width=\"0.25\"/><line class=\"p\" x1=\"-7.62\" y1=\"0\" x2=\"-5.08\" y2=\"0\"/><line class=\"p\" x1=\"-5.08\" y1=\"5.08\" x2=\"-2.54\" y2=\"5.08\"/><line class=\"p\" x1=\"-5.08\" y1=\"2.54\" x2=\"-2.54\" y2=\"2.54\"/><line class=\"p\" x1=\"-5.08\" y1=\"-2.54\" x2=\"-2.54\" y2=\"-2.54\"/><line class=\"p\" x1=\"-2.54\" y1=\"7.62\" x2=\"-2.54\" y2=\"3.81\"/><line class=\"p\" x1=\"-2.54\" y1=\"-7.62\" x2=\"-2.54\" y2=\"-3.81\"/><line class=\"p\" x1=\"0\" y1=\"-7.62\" x2=\"0\" y2=\"-2.54\"/><line class=\"p\" x1=\"7.62\" y1=\"0\" x2=\"5.08\" y2=\"0\"/></svg>","EL2001CN":"<svg xmlns=\"http://www.w3.org/2000/svg\" viewBox=\"-8.84 -8.84 17.68 17.68\"><style>.s{stroke:rgb(132,0,0);stroke-linecap:round;stroke-linejoin:round;fill:none}.p{stroke:rgb(132,0,0);stroke-width:0.1524;stroke-linecap:round;fill:none}.fo{fill:rgb(132,0,0)}.fb{fill:rgb(255,255,194)}</style><polygon class=\"s fb\" points=\"5.08,0 -5.08,5.08 -5.08,-5.08 5.08,0\" stroke-width=\"0.25\"/><line class=\"p\" x1=\"-7.62\" y1=\"0\" x2=\"-5.08\" y2=\"0\"/><line class=\"p\" x1=\"-5.08\" y1=\"5.08\" x2=\"-2.54\" y2=\"5.08\"/><line class=\"p\" x1=\"-5.08\" y1=\"2.54\" x2=\"-2.54\" y2=\"2.54\"/><line class=\"p\" x1=\"-5.08\" y1=\"-2.54\" x2=\"-2.54\" y2=\"-2.54\"/><line class=\"p\" x1=\"-5.08\" y1=\"-5.08\" x2=\"-2.54\" y2=\"-5.08\"/><line class=\"p\" x1=\"-2.54\" y1=\"7.62\" x2=\"-2.54\" y2=\"3.81\"/><line class=\"p\" x1=\"-2.54\" y1=\"-7.62\" x2=\"-2.54\" y2=\"-3.81\"/><line class=\"p\" x1=\"7.62\" y1=\"0\" x2=\"5.08\" y2=\"0\"/></svg>","LH0002H":"<svg xmlns=\"http://www.w3.org/2000/svg\" viewBox=\"-8.84 -8.84 17.68 17.68\"><style>.s{stroke:rgb(132,0,0);stroke-linecap:round;stroke-linejoin:round;fill:none}.p{stroke:rgb(132,0,0);stroke-width:0.1524;stroke-linecap:round;fill:none}.fo{fill:rgb(132,0,0)}.fb{fill:rgb(255,255,194)}</style><polygon class=\"s fb\" points=\"5.08,0 -5.08,5.08 -5.08,-5.08 5.08,0\" stroke-width=\"0.25\"/><line class=\"p\" x1=\"-7.62\" y1=\"0\" x2=\"-5.08\" y2=\"0\"/><line class=\"p\" x1=\"-2.54\" y1=\"7.62\" x2=\"-2.54\" y2=\"3.81\"/><line class=\"p\" x1=\"-2.54\" y1=\"-7.62\" x2=\"-2.54\" y2=\"-3.81\"/><line class=\"p\" x1=\"0\" y1=\"7.62\" x2=\"0\" y2=\"2.54\"/><line class=\"p\" x1=\"0\" y1=\"-7.62\" x2=\"0\" y2=\"-2.54\"/><line class=\"p\" x1=\"2.54\" y1=\"7.62\" x2=\"2.54\" y2=\"1.27\"/><line class=\"p\" x1=\"2.54\" y1=\"-7.62\" x2=\"2.54\" y2=\"-1.27\"/><line class=\"p\" x1=\"7.62\" y1=\"0\" x2=\"5.08\" y2=\"0\"/></svg>","LM6321H":"<svg xmlns=\"http://www.w3.org/2000/svg\" viewBox=\"-8.84 -8.84 17.68 17.68\"><style>.s{stroke:rgb(132,0,0);stroke-linecap:round;stroke-linejoin:round;fill:none}.p{stroke:rgb(132,0,0);stroke-width:0.1524;stroke-linecap:round;fill:none}.fo{fill:rgb(132,0,0)}.fb{fill:rgb(255,255,194)}</style><polygon class=\"s fb\" points=\"5.08,0 -5.08,5.08 -5.08,-5.08 5.08,0\" stroke-width=\"0.25\"/><line class=\"p\" x1=\"-7.62\" y1=\"0\" x2=\"-5.08\" y2=\"0\"/><line class=\"p\" x1=\"-2.54\" y1=\"7.62\" x2=\"-2.54\" y2=\"3.81\"/><line class=\"p\" x1=\"-2.54\" y1=\"2.54\" x2=\"-2.54\" y2=\"0\"/><line class=\"p\" x1=\"-2.54\" y1=\"-2.54\" x2=\"-2.54\" y2=\"0\"/><line class=\"p\" x1=\"-2.54\" y1=\"-7.62\" x2=\"-2.54\" y2=\"-3.81\"/><line class=\"p\" x1=\"0\" y1=\"2.54\" x2=\"0\" y2=\"0\"/><line class=\"p\" x1=\"0\" y1=\"-2.54\" x2=\"0\" y2=\"0\"/><line class=\"p\" x1=\"7.62\" y1=\"0\" x2=\"5.08\" y2=\"0\"/></svg>","LM6321M":"<svg xmlns=\"http://www.w3.org/2000/svg\" viewBox=\"-8.84 -8.84 17.68 17.68\"><style>.s{stroke:rgb(132,0,0);stroke-linecap:round;stroke-linejoin:round;fill:none}.p{stroke:rgb(132,0,0);stroke-width:0.1524;stroke-linecap:round;fill:none}.fo{fill:rgb(132,0,0)}.fb{fill:rgb(255,255,194)}</style><polygon class=\"s fb\" points=\"5.08,0 -5.08,5.08 -5.08,-5.08 5.08,0\" stroke-width=\"0.25\"/><line class=\"p\" x1=\"-7.62\" y1=\"0\" x2=\"-5.08\" y2=\"0\"/><line class=\"p\" x1=\"-2.54\" y1=\"7.62\" x2=\"-2.54\" y2=\"3.81\"/><line class=\"p\" x1=\"-2.54\" y1=\"-7.62\" x2=\"-2.54\" y2=\"-3.81\"/><line class=\"p\" x1=\"-2.54\" y1=\"-7.62\" x2=\"-2.54\" y2=\"-3.81\"/><line class=\"p\" x1=\"-2.54\" y1=\"-7.62\" x2=\"-2.54\" y2=\"-3.81\"/><line class=\"p\" x1=\"-2.54\" y1=\"-7.62\" x2=\"-2.54\" y2=\"-3.81\"/><line class=\"p\" x1=\"-2.54\" y1=\"-7.62\" x2=\"-2.54\" y2=\"-3.81\"/><line class=\"p\" x1=\"-2.54\" y1=\"-7.62\" x2=\"-2.54\" y2=\"-3.81\"/><line class=\"p\" x1=\"-2.54\" y1=\"-7.62\" x2=\"-2.54\" y2=\"-3.81\"/><line class=\"p\" x1=\"-2.54\" y1=\"-7.62\" x2=\"-2.54\" y2=\"-3.81\"/><line class=\"p\" x1=\"-2.54\" y1=\"-7.62\" x2=\"-2.54\" y2=\"-3.81\"/><line class=\"p\" x1=\"0\" y1=\"2.54\" x2=\"0\" y2=\"0\"/><line class=\"p\" x1=\"0\" y1=\"-2.54\" x2=\"0\" y2=\"0\"/><line class=\"p\" x1=\"7.62\" y1=\"0\" x2=\"5.08\" y2=\"0\"/></svg>","LM6321N":"<svg xmlns=\"http://www.w3.org/2000/svg\" viewBox=\"-8.84 -8.84 17.68 17.68\"><style>.s{stroke:rgb(132,0,0);stroke-linecap:round;stroke-linejoin:round;fill:none}.p{stroke:rgb(132,0,0);stroke-width:0.1524;stroke-linecap:round;fill:none}.fo{fill:rgb(132,0,0)}.fb{fill:rgb(255,255,194)}</style><polygon class=\"s fb\" points=\"5.08,0 -5.08,5.08 -5.08,-5.08 5.08,0\" stroke-width=\"0.25\"/><line class=\"p\" x1=\"-7.62\" y1=\"0\" x2=\"-5.08\" y2=\"0\"/><line class=\"p\" x1=\"-2.54\" y1=\"7.62\" x2=\"-2.54\" y2=\"3.81\"/><line class=\"p\" x1=\"-2.54\" y1=\"2.54\" x2=\"-2.54\" y2=\"0\"/><line class=\"p\" x1=\"-2.54\" y1=\"-2.54\" x2=\"-2.54\" y2=\"0\"/><line class=\"p\" x1=\"-2.54\" y1=\"-7.62\" x2=\"-2.54\" y2=\"-3.81\"/><line class=\"p\" x1=\"0\" y1=\"2.54\" x2=\"0\" y2=\"0\"/><line class=\"p\" x1=\"0\" y1=\"-2.54\" x2=\"0\" y2=\"0\"/><line class=\"p\" x1=\"7.62\" y1=\"0\" x2=\"5.08\" y2=\"0\"/></svg>","BUF634AxD":"<svg xmlns=\"http://www.w3.org/2000/svg\" viewBox=\"-8.84 -8.84 17.68 17.68\"><style>.s{stroke:rgb(132,0,0);stroke-linecap:round;stroke-linejoin:round;fill:none}.p{stroke:rgb(132,0,0);stroke-width:0.1524;stroke-linecap:round;fill:none}.fo{fill:rgb(132,0,0)}.fb{fill:rgb(255,255,194)}</style><polygon class=\"s fb\" points=\"5.08,0 -5.08,5.08 -5.08,-5.08 5.08,0\" stroke-width=\"0.25\"/><line class=\"p\" x1=\"-7.62\" y1=\"0\" x2=\"-5.08\" y2=\"0\"/><line class=\"p\" x1=\"-5.08\" y1=\"5.08\" x2=\"-2.54\" y2=\"5.08\"/><line class=\"p\" x1=\"-5.08\" y1=\"2.54\" x2=\"-2.54\" y2=\"2.54\"/><line class=\"p\" x1=\"-5.08\" y1=\"-2.54\" x2=\"-2.54\" y2=\"-2.54\"/><line class=\"p\" x1=\"-2.54\" y1=\"7.62\" x2=\"-2.54\" y2=\"3.81\"/><line class=\"p\" x1=\"-2.54\" y1=\"-7.62\" x2=\"-2.54\" y2=\"-3.81\"/><line class=\"p\" x1=\"0\" y1=\"-7.62\" x2=\"0\" y2=\"-2.54\"/><line class=\"p\" x1=\"7.62\" y1=\"0\" x2=\"5.08\" y2=\"0\"/></svg>","BUF634AxDRB":"<svg xmlns=\"http://www.w3.org/2000/svg\" viewBox=\"-8.84 -8.84 17.68 17.68\"><style>.s{stroke:rgb(132,0,0);stroke-linecap:round;stroke-linejoin:round;fill:none}.p{stroke:rgb(132,0,0);stroke-width:0.1524;stroke-linecap:round;fill:none}.fo{fill:rgb(132,0,0)}.fb{fill:rgb(255,255,194)}</style><polygon class=\"s fb\" points=\"5.08,0 -5.08,5.08 -5.08,-5.08 5.08,0\" stroke-width=\"0.25\"/><line class=\"p\" x1=\"0\" y1=\"-7.62\" x2=\"0\" y2=\"-2.54\"/><line class=\"p\" x1=\"-7.62\" y1=\"0\" x2=\"-5.08\" y2=\"0\"/><line class=\"p\" x1=\"-5.08\" y1=\"5.08\" x2=\"-2.54\" y2=\"5.08\"/><line class=\"p\" x1=\"-5.08\" y1=\"2.54\" x2=\"-2.54\" y2=\"2.54\"/><line class=\"p\" x1=\"-5.08\" y1=\"-2.54\" x2=\"-2.54\" y2=\"-2.54\"/><line class=\"p\" x1=\"-2.54\" y1=\"7.62\" x2=\"-2.54\" y2=\"3.81\"/><line class=\"p\" x1=\"-2.54\" y1=\"-7.62\" x2=\"-2.54\" y2=\"-3.81\"/><line class=\"p\" x1=\"2.54\" y1=\"-7.62\" x2=\"2.54\" y2=\"-1.27\"/><line class=\"p\" x1=\"7.62\" y1=\"0\" x2=\"5.08\" y2=\"0\"/></svg>"}